lognplot/__init__.py
lognplot/__main__.py
lognplot/callstackbar.py
lognplot/client.py
lognplot/demo_data.py
lognplot/utils.py
lognplot/chart/__init__.py
lognplot/chart/axis.py
lognplot/chart/chart.py
lognplot/chart/curve.py
lognplot/chart/event_tracks.py
lognplot/chart/logbar.py
lognplot/qt/__init__.py
lognplot/qt/qtapi.py
lognplot/qt/apps/__init__.py
lognplot/qt/apps/server_gui.py
lognplot/qt/render/__init__.py
lognplot/qt/render/base.py
lognplot/qt/render/chart.py
lognplot/qt/render/event.py
lognplot/qt/render/layout.py
lognplot/qt/render/log.py
lognplot/qt/render/options.py
lognplot/qt/render/render.py
lognplot/qt/render/transform.py
lognplot/qt/widgets/__init__.py
lognplot/qt/widgets/basewidget.py
lognplot/qt/widgets/callstackwidget.py
lognplot/qt/widgets/chartwidget.py
lognplot/qt/widgets/dashboard.py
lognplot/qt/widgets/db_proxy.py
lognplot/qt/widgets/db_tree_model.py
lognplot/qt/widgets/eventwidget.py
lognplot/qt/widgets/logwidget.py
lognplot/qt/widgets/mime.py
lognplot/qt/widgets/signal_list_widget.py
lognplot/qt/widgets/softscope.py
lognplot/qt/widgets/timespan_toolbutton.py
lognplot/server/__init__.py
lognplot/server/connection.py
lognplot/server/peer.py
lognplot/server/server.py
lognplot/time/__init__.py
lognplot/time/duration.py
lognplot/time/timespan.py
lognplot/tsdb/__init__.py
lognplot/tsdb/aggregation.py
lognplot/tsdb/btree.py
lognplot/tsdb/db.py
lognplot/tsdb/log.py
lognplot/tsdb/metrics.py
lognplot/tsdb/pager.py
lognplot/tsdb/series.py
lognplot/web/__init__.py
lognplot/web/rest.py
lognplot-0.1.1.dist-info/WHEEL
lognplot-0.1.1.dist-info/METADATA
lognplot-0.1.1.dist-info/RECORD
