Metadata-Version: 2.1
Name: lognplot
Version: 0.1.1
Summary: Log and plot data.
Home-page: https://github.com/windelbouwman/lognplot
License: GPLv3
Keywords: plot
Author: Windel Bouwman
Author-email: windel.bouwman@gmail.com
Requires-Python: >=3.6
Classifier: Topic :: Scientific/Engineering :: Visualization
Classifier: Topic :: System :: Monitoring
Classifier: Topic :: System :: Logging
Classifier: License :: OSI Approved :: GNU General Public License v3 (GPLv3)
Requires-Dist: cbor
